{"stats":{"minecraft:picked_up":{"minecraft:potion":1,"minecraft:armadillo_scute":1},"minecraft:custom":{"minecraft:jump":29,"minecraft:time_since_rest":3928,"minecraft:leave_game":1,"minecraft:sprint_one_cm":2775,"minecraft:play_time":3928,"minecraft:time_since_death":3928,"minecraft:walk_one_cm":10273,"minecraft:sneak_time":39,"minecraft:total_world_time":4752,"minecraft:fly_one_cm":13501},"minecraft:used":{"minecraft:zombie_spawn_egg":3,"allaymaster:white_allay_spawn_egg":1,"allaymaster:red_allay_spawn_egg":1,"minecraft:witch_spawn_egg":1}},"DataVersion":3953}